intake_example_package/__init__.py
intake_example_package/sea.yaml
intake_example_package-0.0.1.dist-info/METADATA
intake_example_package-0.0.1.dist-info/WHEEL
intake_example_package-0.0.1.dist-info/entry_points.txt
intake_example_package-0.0.1.dist-info/top_level.txt
intake_example_package-0.0.1.dist-info/RECORD
